{
	"list1" : [
		{
			"id" : "jiuyou2",
			"title" : "这款酒一直在返购，味道不错，验证是正品，快递小哥送货上门，服务杠杠滴。",
			"phone" : "来自135***7929的评价",
			"Course" : "53度 茅台 赖茅（传承）蓝色 500ml",
			"terms" : "288 元",
			"src" : "images/jiuyou1.png"
		},
				{
			"id" : "jiuyou3",
			"title" : "这个口感还可以，入口醇厚，整箱六瓶，这个价没得话说，一如既往的支持，五星好评",
			"phone" : "来自155***0455的评价",
			"Course" : "拉菲 传奇波尔多AOC 红葡萄酒 750ml*6瓶【整箱装】",
			"terms" : "388 元",
			"src" : "images/jiuyou2.png"
		},
				{
			"id" : "jiuyou4",
			"title" : "虎符令，很漂亮，买来摆柜，包装很好，没有漏酒，快递速度快，最最最重要的是价格便宜，下次还会来买的！",
			"phone" : "来自雅雅的评价",
			"Course" : "52度 五粮液 虎符令 500ml",
			"terms" : "899 元",
			"src" : "images/jiuyou3.png"
		},
				{
			"id" : "jiuyou5",
			"title" : "很赞的酒啊，买几瓶很划算，送的东西也多，购酒网越来越给力了，物流也给力，又快又好的送到了",
			"phone" : "来自154***1994的评价",
			"Course" : "杰克丹尼 田纳西州威士忌 700ml",
			"terms" : "165 元",
			"src" : "images/jiuyou4.png"
		}
	]
}